deepee/__init__.py
deepee/dataloader.py
deepee/privacy_accounting.py
deepee/snooper.py
deepee/surgery.py
deepee/watchdog.py
deepee/wrapper.py
deepee-0.1.9.dist-info/LICENSE
deepee-0.1.9.dist-info/WHEEL
deepee-0.1.9.dist-info/METADATA
deepee-0.1.9.dist-info/RECORD
